{"34642467703@s.whatsapp.net":true,"34642467703:32@s.whatsapp.net":true,"34602210267@s.whatsapp.net":true,"34602210267:5@s.whatsapp.net":true,"34687075780@s.whatsapp.net":true,"34631963983@s.whatsapp.net":true,"34681633674@s.whatsapp.net":true,"34603231278@s.whatsapp.net":true,"34666389241@s.whatsapp.net":true,"34655215858@s.whatsapp.net":true,"34644861483@s.whatsapp.net":true,"15084175825@s.whatsapp.net":true,"34610688568@s.whatsapp.net":true,"34653139697@s.whatsapp.net":true,"34654052664@s.whatsapp.net":true,"34654052664:3@s.whatsapp.net":true,"34605526334@s.whatsapp.net":true,"34688646137@s.whatsapp.net":true,"34624043763@s.whatsapp.net":true,"34717147702@s.whatsapp.net":true,"34660528642@s.whatsapp.net":true,"34602364742@s.whatsapp.net":true,"34678261188@s.whatsapp.net":true,"34624621244@s.whatsapp.net":true,"34603264411@s.whatsapp.net":true,"34611190623@s.whatsapp.net":true,"34671195335@s.whatsapp.net":true,"34631224204@s.whatsapp.net":true,"34631860866@s.whatsapp.net":true,"34635564981@s.whatsapp.net":true,"34603040300@s.whatsapp.net":true,"34603040300:9@s.whatsapp.net":true,"34675752177@s.whatsapp.net":true,"34625897166@s.whatsapp.net":true,"34621062880@s.whatsapp.net":true,"34645332861@s.whatsapp.net":true,"34643680639@s.whatsapp.net":true,"34640122248@s.whatsapp.net":true,"34625047377@s.whatsapp.net":true,"34643343813@s.whatsapp.net":true,"34631293939@s.whatsapp.net":true,"34631293939:5@s.whatsapp.net":true,"34631293939:6@s.whatsapp.net":true,"34613456818@s.whatsapp.net":true,"34603696959@s.whatsapp.net":true,"34639534188@s.whatsapp.net":true,"34722388499@s.whatsapp.net":true,"34611300195@s.whatsapp.net":true,"34671244373@s.whatsapp.net":true,"34613942599@s.whatsapp.net":true,"34633838579@s.whatsapp.net":true,"34680186122@s.whatsapp.net":true,"34600981590@s.whatsapp.net":true,"34630946896@s.whatsapp.net":true,"34601418756@s.whatsapp.net":true,"34722580014@s.whatsapp.net":true,"34658895829@s.whatsapp.net":true,"34603858646@s.whatsapp.net":true,"34621315642@s.whatsapp.net":true,"34621315642:8@s.whatsapp.net":true,"34663814652@s.whatsapp.net":true,"34641939642@s.whatsapp.net":true,"34603149124@s.whatsapp.net":true,"34642398998@s.whatsapp.net":true,"34631323191@s.whatsapp.net":true,"34625373300@s.whatsapp.net":true,"34625373300:31@s.whatsapp.net":true,"34722685873@s.whatsapp.net":true,"34642248168@s.whatsapp.net":true,"34641662596@s.whatsapp.net":true,"5491142840093@s.whatsapp.net":true,"34633316697@s.whatsapp.net":true,"34640574968@s.whatsapp.net":true,"34623311305@s.whatsapp.net":true,"34697893046@s.whatsapp.net":true,"15635380242@s.whatsapp.net":true,"34665235191@s.whatsapp.net":true,"34665235191:9@s.whatsapp.net":true,"34682912190@s.whatsapp.net":true,"34635800900@s.whatsapp.net":true,"34628282103@s.whatsapp.net":true,"34673130646@s.whatsapp.net":true,"34606881795@s.whatsapp.net":true,"34603563736@s.whatsapp.net":true,"34722270327@s.whatsapp.net":true,"34609064500@s.whatsapp.net":true,"12155406030@s.whatsapp.net":true,"34645824543@s.whatsapp.net":true,"34641072271@s.whatsapp.net":true,"34697697427@s.whatsapp.net":true,"34722438593@s.whatsapp.net":true,"34684034703@s.whatsapp.net":true,"34665314537@s.whatsapp.net":true,"34611529887@s.whatsapp.net":true,"34611529887:8@s.whatsapp.net":true,"34644467338@s.whatsapp.net":true,"34644467338:4@s.whatsapp.net":true,"34640863896@s.whatsapp.net":true,"34603461018@s.whatsapp.net":true,"34603461018:6@s.whatsapp.net":true,"34603461018:7@s.whatsapp.net":true,"34646129891@s.whatsapp.net":true,"34603022140@s.whatsapp.net":true,"18593502667@s.whatsapp.net":true,"34639226006@s.whatsapp.net":true,"34622959155@s.whatsapp.net":true,"34643646423@s.whatsapp.net":true,"34602651894@s.whatsapp.net":true,"34608390787@s.whatsapp.net":true,"14154219244@s.whatsapp.net":true,"34605532913@s.whatsapp.net":true,"34644483380@s.whatsapp.net":true,"34629856362@s.whatsapp.net":true,"34695231359@s.whatsapp.net":true,"34674390881@s.whatsapp.net":true,"34644511274@s.whatsapp.net":true,"34642290697@s.whatsapp.net":true,"34682182631@s.whatsapp.net":true,"17343710058@s.whatsapp.net":true,"34624179922@s.whatsapp.net":true,"34622111271@s.whatsapp.net":true,"34622709228@s.whatsapp.net":true,"34611124784@s.whatsapp.net":true,"34693246003@s.whatsapp.net":true,"34658502194@s.whatsapp.net":true,"34645245609@s.whatsapp.net":true,"34645245609:12@s.whatsapp.net":true,"34645245609:13@s.whatsapp.net":true,"34677817060@s.whatsapp.net":true,"5355165259@s.whatsapp.net":true,"35722090140@s.whatsapp.net":true,"34642985709@s.whatsapp.net":true,"34671969712@s.whatsapp.net":true,"34671969712:21@s.whatsapp.net":true,"34611081765@s.whatsapp.net":true,"34602408417@s.whatsapp.net":true,"34681981460@s.whatsapp.net":true,"34686751200@s.whatsapp.net":true,"34603334885@s.whatsapp.net":true,"16096916720@s.whatsapp.net":true,"34633411302@s.whatsapp.net":true,"34633411302:6@s.whatsapp.net":true,"34644845102@s.whatsapp.net":true,"34642793819@s.whatsapp.net":true,"34643172615@s.whatsapp.net":true,"34600883130@s.whatsapp.net":true,"34603331165@s.whatsapp.net":true,"34645358811@s.whatsapp.net":true,"34682325127@s.whatsapp.net":true,"34632259249@s.whatsapp.net":true,"34684174387@s.whatsapp.net":true,"34651829088@s.whatsapp.net":true,"34629924188@s.whatsapp.net":true,"34691860163@s.whatsapp.net":true,"34643422459@s.whatsapp.net":true,"34613592089@s.whatsapp.net":true,"34693503376@s.whatsapp.net":true,"34627924057@s.whatsapp.net":true,"34663242965@s.whatsapp.net":true,"40764678492@s.whatsapp.net":true,"34678205311@s.whatsapp.net":true,"34654410918@s.whatsapp.net":true,"34654410918:7@s.whatsapp.net":true,"34644720041@s.whatsapp.net":true,"34664028818@s.whatsapp.net":true,"32466900294@s.whatsapp.net":true,"34622905671@s.whatsapp.net":true,"34610128584@s.whatsapp.net":true,"34667032668@s.whatsapp.net":true,"34640061582@s.whatsapp.net":true,"34631656169@s.whatsapp.net":true,"34640166972@s.whatsapp.net":true,"34626545975@s.whatsapp.net":true,"34644316478@s.whatsapp.net":true,"34617240819@s.whatsapp.net":true,"34624504429@s.whatsapp.net":true,"34699104072@s.whatsapp.net":true,"13022613165@s.whatsapp.net":true,"34669510130@s.whatsapp.net":true,"34693689119@s.whatsapp.net":true,"34622731371@s.whatsapp.net":true,"34640192423@s.whatsapp.net":true,"34603448394@s.whatsapp.net":true,"34635095711@s.whatsapp.net":true,"34642539765@s.whatsapp.net":true,"33779221357@s.whatsapp.net":true,"34633963456@s.whatsapp.net":true,"34622207217@s.whatsapp.net":true,"34633261193@s.whatsapp.net":true,"34688413677@s.whatsapp.net":true,"34645565590@s.whatsapp.net":true,"34675857922@s.whatsapp.net":true,"34621033525@s.whatsapp.net":true,"34722413414@s.whatsapp.net":true,"34636947835@s.whatsapp.net":true,"34623319609@s.whatsapp.net":true,"34633436527@s.whatsapp.net":true,"34684241623@s.whatsapp.net":true,"34615709834@s.whatsapp.net":true,"34629351607@s.whatsapp.net":true,"34631223730@s.whatsapp.net":true,"34658401392@s.whatsapp.net":true,"34608197030@s.whatsapp.net":true,"34662442062@s.whatsapp.net":true,"34613940630@s.whatsapp.net":true,"34602072042@s.whatsapp.net":true,"34613323193@s.whatsapp.net":true,"34695792197@s.whatsapp.net":true,"34695792197:2@s.whatsapp.net":true,"34680537520@s.whatsapp.net":true,"34641541950@s.whatsapp.net":true,"34661117214@s.whatsapp.net":true,"34634799245@s.whatsapp.net":true,"34632010894@s.whatsapp.net":true,"34648174997@s.whatsapp.net":true,"34722290973@s.whatsapp.net":true,"34601325501@s.whatsapp.net":true,"447360250759@s.whatsapp.net":true,"34627133117@s.whatsapp.net":true,"34633827762@s.whatsapp.net":true,"34611443664@s.whatsapp.net":true,"34613521905@s.whatsapp.net":true,"34636595276@s.whatsapp.net":true,"34641711554@s.whatsapp.net":true,"34600021406@s.whatsapp.net":true,"34671792289@s.whatsapp.net":true,"34641474734@s.whatsapp.net":true,"34637879826@s.whatsapp.net":true,"34600076329@s.whatsapp.net":true,"34622814612@s.whatsapp.net":true,"34622814612:12@s.whatsapp.net":true,"34622814612:13@s.whatsapp.net":true,"34611147940@s.whatsapp.net":true,"34641639149@s.whatsapp.net":true,"34636711147@s.whatsapp.net":true,"34602052380@s.whatsapp.net":true,"595983058876@s.whatsapp.net":true,"34667068537@s.whatsapp.net":true,"34635057515@s.whatsapp.net":true,"34610625608@s.whatsapp.net":true,"34643180317@s.whatsapp.net":true,"34604397629@s.whatsapp.net":true,"34685508100@s.whatsapp.net":true,"34602219124@s.whatsapp.net":true,"34602219124:7@s.whatsapp.net":true,"34602219124:8@s.whatsapp.net":true,"34657929189@s.whatsapp.net":true,"34624663781@s.whatsapp.net":true,"34651710242@s.whatsapp.net":true,"34602539200@s.whatsapp.net":true,"34602539200:2@s.whatsapp.net":true,"34665906332@s.whatsapp.net":true,"34646822361@s.whatsapp.net":true,"34602677510@s.whatsapp.net":true,"34655673571@s.whatsapp.net":true,"34617839219@s.whatsapp.net":true,"34635150605@s.whatsapp.net":true,"34643302672@s.whatsapp.net":true,"34670291944@s.whatsapp.net":true,"34670291944:1@s.whatsapp.net":true,"34633747319@s.whatsapp.net":true,"34633232292@s.whatsapp.net":true,"34640224656@s.whatsapp.net":true,"34633581931@s.whatsapp.net":true,"16155494891@s.whatsapp.net":true,"5491137017879@s.whatsapp.net":true,"34622825567@s.whatsapp.net":true,"34626859865@s.whatsapp.net":true,"34683353085@s.whatsapp.net":true,"34652787547@s.whatsapp.net":true,"34698958279@s.whatsapp.net":true,"34641630382@s.whatsapp.net":true,"34610983989@s.whatsapp.net":true,"34644931607@s.whatsapp.net":true,"34615660660@s.whatsapp.net":true,"34615660660:1@s.whatsapp.net":true,"34654087073@s.whatsapp.net":true,"34676322956@s.whatsapp.net":true,"34612480801@s.whatsapp.net":true,"34615703854@s.whatsapp.net":true,"34685382696@s.whatsapp.net":true,"34691820518@s.whatsapp.net":true,"34634433965@s.whatsapp.net":true,"34600519179@s.whatsapp.net":true,"34744680018@s.whatsapp.net":true,"34642854126@s.whatsapp.net":true,"34680553333@s.whatsapp.net":true,"34640216142@s.whatsapp.net":true,"34620050543@s.whatsapp.net":true,"34611626596@s.whatsapp.net":true,"34607046943@s.whatsapp.net":true,"34629764159@s.whatsapp.net":true,"34602866912@s.whatsapp.net":true,"34624352002@s.whatsapp.net":true,"14094193304@s.whatsapp.net":true,"34617337910@s.whatsapp.net":true,"34663475163@s.whatsapp.net":true,"34652279770@s.whatsapp.net":true,"34603825190@s.whatsapp.net":true,"34631138636@s.whatsapp.net":true,"34628410907@s.whatsapp.net":true,"34628410907:20@s.whatsapp.net":true,"34628410907:23@s.whatsapp.net":true,"34602350965@s.whatsapp.net":true,"34663130719@s.whatsapp.net":true,"34680222818@s.whatsapp.net":true,"34601298899@s.whatsapp.net":true,"34641166541@s.whatsapp.net":true,"34643626532@s.whatsapp.net":true,"34658684896@s.whatsapp.net":true,"34658684896:3@s.whatsapp.net":true,"34658684896:95@s.whatsapp.net":true,"34643023399@s.whatsapp.net":true,"34642656941@s.whatsapp.net":true,"34642656941:15@s.whatsapp.net":true,"34644460983@s.whatsapp.net":true,"34603732738@s.whatsapp.net":true,"34632940064@s.whatsapp.net":true,"34642219882@s.whatsapp.net":true,"34644513448@s.whatsapp.net":true,"34641452848@s.whatsapp.net":true,"34722477310@s.whatsapp.net":true,"34640791604@s.whatsapp.net":true,"34630961234@s.whatsapp.net":true,"34641302142@s.whatsapp.net":true,"34619673060@s.whatsapp.net":true,"34678100911@s.whatsapp.net":true,"34640100643@s.whatsapp.net":true,"34653859892@s.whatsapp.net":true,"50664070347@s.whatsapp.net":true,"34643449295@s.whatsapp.net":true,"34611267719@s.whatsapp.net":true,"34654625718@s.whatsapp.net":true,"34655773319@s.whatsapp.net":true,"34633111305@s.whatsapp.net":true,"34622890674@s.whatsapp.net":true,"34698707821@s.whatsapp.net":true,"34698707821:1@s.whatsapp.net":true,"34698707821:96@s.whatsapp.net":true,"34698707821:97@s.whatsapp.net":true,"34669821442@s.whatsapp.net":true,"34669821442:3@s.whatsapp.net":true,"34607382384@s.whatsapp.net":true,"5492612763885@s.whatsapp.net":true,"16092374891@s.whatsapp.net":true,"34682322914@s.whatsapp.net":true,"34691042117@s.whatsapp.net":true,"34601135654@s.whatsapp.net":true,"5216442398639@s.whatsapp.net":true,"34625284653@s.whatsapp.net":true,"34604064859@s.whatsapp.net":true,"34608261914@s.whatsapp.net":true,"34608261914:6@s.whatsapp.net":true,"34656663171@s.whatsapp.net":true,"34655308380@s.whatsapp.net":true,"34653319002@s.whatsapp.net":true,"34603835731@s.whatsapp.net":true,"34644468069@s.whatsapp.net":true,"34644468069:1@s.whatsapp.net":true,"34722654803@s.whatsapp.net":true,"5492613660329@s.whatsapp.net":true,"34657319337@s.whatsapp.net":true,"34601150548@s.whatsapp.net":true,"34647251882@s.whatsapp.net":true,"34624236513@s.whatsapp.net":true,"34624236513:14@s.whatsapp.net":true,"34640364560@s.whatsapp.net":true,"34655798493@s.whatsapp.net":true,"40757983478@s.whatsapp.net":true,"34609110021@s.whatsapp.net":true,"34645105900@s.whatsapp.net":true,"34621364603@s.whatsapp.net":true,"34631329363@s.whatsapp.net":true,"34644652135@s.whatsapp.net":true,"34667262067@s.whatsapp.net":true,"34648451710@s.whatsapp.net":true,"34689650578@s.whatsapp.net":true,"34644832451@s.whatsapp.net":true,"34644832451:4@s.whatsapp.net":true,"34722887701@s.whatsapp.net":true,"34676926206@s.whatsapp.net":true,"34669410681@s.whatsapp.net":true,"34610249019@s.whatsapp.net":true,"34662668537@s.whatsapp.net":true,"34622947240@s.whatsapp.net":true,"34668682063@s.whatsapp.net":true,"34668682063:9@s.whatsapp.net":true,"34668682063:10@s.whatsapp.net":true,"34613170191@s.whatsapp.net":true,"34608422461@s.whatsapp.net":true,"34676990029@s.whatsapp.net":true,"34637468160@s.whatsapp.net":true,"14129913304@s.whatsapp.net":true,"34628597125@s.whatsapp.net":true,"34653629471@s.whatsapp.net":true,"34613023190@s.whatsapp.net":true,"34617308277@s.whatsapp.net":true,"34650809868@s.whatsapp.net":true,"34651875344@s.whatsapp.net":true,"34626638167@s.whatsapp.net":true,"34664681223@s.whatsapp.net":true,"34615565067@s.whatsapp.net":true,"34617483183@s.whatsapp.net":true,"34658261092@s.whatsapp.net":true,"34624248330@s.whatsapp.net":true,"34663860807@s.whatsapp.net":true,"34610622836@s.whatsapp.net":true,"34601360421@s.whatsapp.net":true,"34651310835@s.whatsapp.net":true,"34643767652@s.whatsapp.net":true,"34747769487@s.whatsapp.net":true,"34615438328@s.whatsapp.net":true,"34609141523@s.whatsapp.net":true,"12313590022@s.whatsapp.net":true,"34676694235@s.whatsapp.net":true,"5216442385224@s.whatsapp.net":true,"34651049428@s.whatsapp.net":true,"34676210906@s.whatsapp.net":true,"34603297590@s.whatsapp.net":true,"34660750181@s.whatsapp.net":true,"34600922444@s.whatsapp.net":true,"34722251320@s.whatsapp.net":true,"34643402585@s.whatsapp.net":true,"34626621337@s.whatsapp.net":true,"34641961152@s.whatsapp.net":true,"34688766907@s.whatsapp.net":true,"34603582315@s.whatsapp.net":true,"34641793898@s.whatsapp.net":true,"34627488208@s.whatsapp.net":true,"46731295139@s.whatsapp.net":true,"34642336491@s.whatsapp.net":true,"34634822821@s.whatsapp.net":true,"34634822821:14@s.whatsapp.net":true,"34634822821:15@s.whatsapp.net":true,"34664482943@s.whatsapp.net":true,"34651323102@s.whatsapp.net":true,"34675829600@s.whatsapp.net":true,"34632956174@s.whatsapp.net":true,"34632956174:41@s.whatsapp.net":true,"34662063213@s.whatsapp.net":true,"34644840154@s.whatsapp.net":true,"34613826686@s.whatsapp.net":true,"34647827037@s.whatsapp.net":true,"34633013038@s.whatsapp.net":true,"34664479457@s.whatsapp.net":true,"34747868658@s.whatsapp.net":true,"34623317826@s.whatsapp.net":true,"34623317826:14@s.whatsapp.net":true,"5493513089032@s.whatsapp.net":true,"34604948486@s.whatsapp.net":true,"34659889606@s.whatsapp.net":true,"34644758774@s.whatsapp.net":true,"34603351874@s.whatsapp.net":true,"34631630890@s.whatsapp.net":true,"34722572665@s.whatsapp.net":true,"34626390260@s.whatsapp.net":true,"34664199304@s.whatsapp.net":true,"34690078201@s.whatsapp.net":true,"17622607994@s.whatsapp.net":true,"34634296570@s.whatsapp.net":true,"34631308590@s.whatsapp.net":true,"34675893757@s.whatsapp.net":true,"34641530692@s.whatsapp.net":true,"34623383132@s.whatsapp.net":true,"34660337485@s.whatsapp.net":true,"34657678592@s.whatsapp.net":true,"34662009242@s.whatsapp.net":true,"34643969309@s.whatsapp.net":true,"34662471857@s.whatsapp.net":true,"5493764390278@s.whatsapp.net":true,"34663520713@s.whatsapp.net":true,"34658395461@s.whatsapp.net":true,"5493518049380@s.whatsapp.net":true,"34644241773@s.whatsapp.net":true,"34608742553@s.whatsapp.net":true,"34608742553:80@s.whatsapp.net":true,"34623199380@s.whatsapp.net":true,"34640197801@s.whatsapp.net":true,"34722172243@s.whatsapp.net":true,"34643252202@s.whatsapp.net":true,"34693653054@s.whatsapp.net":true,"34691580873@s.whatsapp.net":true,"34623298681@s.whatsapp.net":true,"34605506201@s.whatsapp.net":true,"34661039292@s.whatsapp.net":true,"34693802965@s.whatsapp.net":true,"17862781122@s.whatsapp.net":true,"34643419149@s.whatsapp.net":true,"34644099377@s.whatsapp.net":true,"34641986663@s.whatsapp.net":true,"34691230051@s.whatsapp.net":true,"34601477875@s.whatsapp.net":true,"34622047228@s.whatsapp.net":true,"34645832804@s.whatsapp.net":true,"34622249171@s.whatsapp.net":true,"13232326846@s.whatsapp.net":true,"34624851697@s.whatsapp.net":true,"34665851827@s.whatsapp.net":true,"34632017312@s.whatsapp.net":true,"34634725898@s.whatsapp.net":true,"34651771907@s.whatsapp.net":true,"34635737244@s.whatsapp.net":true,"34677350789@s.whatsapp.net":true,"34643538769@s.whatsapp.net":true,"34653567654@s.whatsapp.net":true,"34665888357@s.whatsapp.net":true,"34611238948@s.whatsapp.net":true,"34616607623@s.whatsapp.net":true,"34640063733@s.whatsapp.net":true,"34652225185@s.whatsapp.net":true,"34612506116@s.whatsapp.net":true,"34960730490@s.whatsapp.net":true,"34646886935@s.whatsapp.net":true,"34602813014@s.whatsapp.net":true,"34692044046@s.whatsapp.net":true,"34692044046:7@s.whatsapp.net":true,"34642663933@s.whatsapp.net":true,"34642663933:2@s.whatsapp.net":true,"34642663933:4@s.whatsapp.net":true,"34622190149@s.whatsapp.net":true,"34641198067@s.whatsapp.net":true,"34622911049@s.whatsapp.net":true,"34632744380@s.whatsapp.net":true,"34643529994@s.whatsapp.net":true,"34644966203@s.whatsapp.net":true,"34644966203:10@s.whatsapp.net":true,"34672496986@s.whatsapp.net":true,"34695465446@s.whatsapp.net":true,"34622861412@s.whatsapp.net":true,"34657630602@s.whatsapp.net":true,"34672388432@s.whatsapp.net":true,"34603665485@s.whatsapp.net":true,"17865605103@s.whatsapp.net":true,"34660672801@s.whatsapp.net":true,"34686394716@s.whatsapp.net":true,"34645769008@s.whatsapp.net":true,"34631110323@s.whatsapp.net":true,"34631110323:8@s.whatsapp.net":true,"34641451635@s.whatsapp.net":true,"50489506678@s.whatsapp.net":true,"34672159924@s.whatsapp.net":true,"34648722928@s.whatsapp.net":true,"34697923756@s.whatsapp.net":true,"34613237412@s.whatsapp.net":true,"34640348506@s.whatsapp.net":true,"34657166434@s.whatsapp.net":true,"34622705721@s.whatsapp.net":true,"34643973153@s.whatsapp.net":true,"34656849821@s.whatsapp.net":true,"34656849821:12@s.whatsapp.net":true,"51932756827@s.whatsapp.net":true,"34722873349@s.whatsapp.net":true,"34651614878@s.whatsapp.net":true,"34650637103@s.whatsapp.net":true,"34650637103:8@s.whatsapp.net":true,"34674822375@s.whatsapp.net":true,"34664793691@s.whatsapp.net":true,"34677617625@s.whatsapp.net":true,"34643302546@s.whatsapp.net":true,"34615376757@s.whatsapp.net":true,"34693024915@s.whatsapp.net":true,"34693024915:12@s.whatsapp.net":true,"34665197734@s.whatsapp.net":true,"34727708724@s.whatsapp.net":true,"34642597511@s.whatsapp.net":true,"13312879232@s.whatsapp.net":true,"34674817022@s.whatsapp.net":true,"34621218543@s.whatsapp.net":true,"34600421089@s.whatsapp.net":true,"34641480585@s.whatsapp.net":true,"34615600821@s.whatsapp.net":true,"34644170453@s.whatsapp.net":true,"34626968950@s.whatsapp.net":true,"34633022003@s.whatsapp.net":true,"34633022003:12@s.whatsapp.net":true,"34621219726@s.whatsapp.net":true,"34623317614@s.whatsapp.net":true,"34634360166@s.whatsapp.net":true,"34677202807@s.whatsapp.net":true,"34619459756@s.whatsapp.net":true,"34643454033@s.whatsapp.net":true,"34646941680@s.whatsapp.net":true,"212632974567@s.whatsapp.net":true,"19899908904@s.whatsapp.net":true,"19564467492@s.whatsapp.net":true,"34666326499@s.whatsapp.net":true,"34624375932@s.whatsapp.net":true,"34693523655@s.whatsapp.net":true,"34608134888@s.whatsapp.net":true,"34611105598@s.whatsapp.net":true,"34635211652@s.whatsapp.net":true,"34631401587@s.whatsapp.net":true,"34674744049@s.whatsapp.net":true,"34653729355@s.whatsapp.net":true,"34653729355:4@s.whatsapp.net":true,"34627185321@s.whatsapp.net":true,"34618112111@s.whatsapp.net":true,"34618112111:24@s.whatsapp.net":true,"13155574468@s.whatsapp.net":true,"34744489346@s.whatsapp.net":true,"34642420419@s.whatsapp.net":true,"34631072278@s.whatsapp.net":true,"34684089142@s.whatsapp.net":true,"34657663562@s.whatsapp.net":true,"34657663562:13@s.whatsapp.net":true,"15155068496@s.whatsapp.net":true,"34615461124@s.whatsapp.net":true,"34664685620@s.whatsapp.net":true,"34642751810@s.whatsapp.net":true,"212665144706@s.whatsapp.net":true,"212665144706:47@s.whatsapp.net":true,"212665144706:68@s.whatsapp.net":true,"34685245769@s.whatsapp.net":true,"34653640009@s.whatsapp.net":true,"34642127717@s.whatsapp.net":true,"34689688208@s.whatsapp.net":true,"34623590696@s.whatsapp.net":true,"5213311535438@s.whatsapp.net":true,"34608333423@s.whatsapp.net":true,"34644188874@s.whatsapp.net":true,"34722699651@s.whatsapp.net":true,"447704039645@s.whatsapp.net":true,"34692928550@s.whatsapp.net":true,"34692928550:11@s.whatsapp.net":true,"34692928550:12@s.whatsapp.net":true,"34693505754@s.whatsapp.net":true,"34642845860@s.whatsapp.net":true,"34643613404@s.whatsapp.net":true,"34695833142@s.whatsapp.net":true,"34605725556@s.whatsapp.net":true,"34605725556:18@s.whatsapp.net":true,"34605725556:19@s.whatsapp.net":true,"34691481362@s.whatsapp.net":true,"34624225039@s.whatsapp.net":true,"34691447934@s.whatsapp.net":true,"34691447934:28@s.whatsapp.net":true,"34637257212@s.whatsapp.net":true,"34684240549@s.whatsapp.net":true,"5218771396336@s.whatsapp.net":true,"34642145960@s.whatsapp.net":true,"34611135032@s.whatsapp.net":true,"34611135032:1@s.whatsapp.net":true,"34636421018@s.whatsapp.net":true,"34632746825@s.whatsapp.net":true,"34605297428@s.whatsapp.net":true,"34626946835@s.whatsapp.net":true,"34633601706@s.whatsapp.net":true,"34641197509@s.whatsapp.net":true,"34641197509:5@s.whatsapp.net":true}